.mailmap
.travis.yml
AUTHORS
ChangeLog
LICENSE
MANIFEST.in
Makefile
Pipfile
Pipfile.lock
README.md
description.rst
example.py
livetests.py
pyproject.toml
requirements.txt
setup.cfg
setup.py
unittests.py
.github/dependabot.yml
pygerrit2/__init__.py
pygerrit2.egg-info/PKG-INFO
pygerrit2.egg-info/SOURCES.txt
pygerrit2.egg-info/dependency_links.txt
pygerrit2.egg-info/not-zip-safe
pygerrit2.egg-info/pbr.json
pygerrit2.egg-info/requires.txt
pygerrit2.egg-info/top_level.txt
pygerrit2/rest/__init__.py
pygerrit2/rest/auth.py