Metadata-Version: 1.1
Name: pygerrit2
Version: 2.0.15
Summary: Client library for interacting with Gerrit's REST API
Home-page: https://github.com/dpursehouse/pygerrit2
Author: David Pursehouse
Author-email: david.pursehouse@gmail.com
License: The MIT License
Keywords: gerrit rest http api client
Platform: POSIX, Unix, MacOS
Classifier: Development Status :: 5 - Production/Stable
Classifier: Environment :: Console
Classifier: Intended Audience :: Developers
Classifier: Intended Audience :: Information Technology
Classifier: License :: OSI Approved :: MIT License
Classifier: Natural Language :: English
Classifier: Programming Language :: Python
Classifier: Programming Language :: Python :: 3.6
Classifier: Programming Language :: Python :: 3.7
Classifier: Programming Language :: Python :: 3.8
Classifier: Operating System :: POSIX
Classifier: Operating System :: Unix
Classifier: Operating System :: MacOS
Classifier: Topic :: Software Development :: Libraries :: Python Modules
